momomail/__init__.py
momomail/gmail/__init__.py
momomail/gmail/client.py
momomail/gmail/exceptions.py
momomail/gmail/label.py
momomail/gmail/message.py
momomail/gmail/thread.py
momomail-2024.3.22.dist-info/LICENSE
momomail-2024.3.22.dist-info/METADATA
momomail-2024.3.22.dist-info/WHEEL
momomail-2024.3.22.dist-info/top_level.txt
momomail-2024.3.22.dist-info/RECORD
