Metadata-Version: 2.1
Name: momomail
Version: 2024.3.22
Summary: Mail Client
Author-email: YYLIZH <ryne91009@gmail.com>
License: MIT License
Project-URL: Homepage, https://github.com/YYLIZH/momomail
Project-URL: Issues, https://github.com/YYLIZH/momomail/issues
Keywords: gmail
Classifier: Programming Language :: Python :: 3
Classifier: License :: OSI Approved :: MIT License
Classifier: Operating System :: OS Independent
Requires-Python: >=3.10
License-File: LICENSE
Requires-Dist: google-api-python-client
Requires-Dist: google-auth-httplib2
Requires-Dist: google-auth-oauthlib
Requires-Dist: pydantic
